dekho_cli/__init__.py
dekho_cli/__main__.py
dekho_cli/main.py
dekho_cli-1.0.3.dist-info/licenses/LICENSE
dekho_cli-1.0.3.dist-info/METADATA
dekho_cli-1.0.3.dist-info/WHEEL
dekho_cli-1.0.3.dist-info/entry_points.txt
dekho_cli-1.0.3.dist-info/top_level.txt
dekho_cli-1.0.3.dist-info/RECORD
