Metadata-Version: 2.4
Name: dekho-cli
Version: 1.0.3
Summary: CLI tool to fetch and play sports channels via mpv.
Author: dev1abhi
Author-email: opguddu21@gmail.com
License: MIT
Classifier: Programming Language :: Python :: 3
Classifier: Operating System :: OS Independent
Requires-Python: >=3.7
License-File: LICENSE
Requires-Dist: requests
Dynamic: author
Dynamic: author-email
Dynamic: classifier
Dynamic: description
Dynamic: description-content-type
Dynamic: license
Dynamic: license-file
Dynamic: requires-dist
Dynamic: requires-python
Dynamic: summary
